vin_decoder/__init__.py
vin_decoder/decode.py
vin_decoder/generate_country_table.py
vin_decoder/generate_manufacturer_table.py
vin_decoder/vdsnissan.py
vin_decoder-0.1.1.data/scripts/vin_decoder
vin_decoder-0.1.1.dist-info/METADATA
vin_decoder-0.1.1.dist-info/RECORD
vin_decoder-0.1.1.dist-info/WHEEL
vin_decoder-0.1.1.dist-info/top_level.txt
